Flow2Spatial/__init__.py
Flow2Spatial/main.py
Flow2Spatial/generator/__init__.py
Flow2Spatial/generator/design_utils.py
Flow2Spatial/generator/generators.py
Flow2Spatial/generator/utils.py
Flow2Spatial/model/__init__.py
Flow2Spatial/model/dnn_utils.py
Flow2Spatial/model/utils.py
Flow2Spatial-0.1.12.dist-info/LICENSE
Flow2Spatial-0.1.12.dist-info/METADATA
Flow2Spatial-0.1.12.dist-info/WHEEL
Flow2Spatial-0.1.12.dist-info/entry_points.txt
Flow2Spatial-0.1.12.dist-info/top_level.txt
Flow2Spatial-0.1.12.dist-info/RECORD
