Metadata-Version: 2.1
Name: Flow2Spatial
Version: 0.1.12
Summary: Reconstructing spatial proteomics through omics transfer learning
Home-page: http://pypi.python.org/pypi/Flow2Spatial/
Author: Ruiqiao He
Author-email: ruiqiaohe@gmail.com
License: GPL
Classifier: Development Status :: 3 - Alpha
Classifier: License :: OSI Approved :: GNU General Public License v3 (GPLv3)
Classifier: Programming Language :: Python :: 3.7
Classifier: Programming Language :: Python :: 3.8
Classifier: Topic :: Scientific/Engineering :: Bio-Informatics
Requires-Python: >=3.7.9
License-File: LICENSE
Requires-Dist: shapely >=1.8.2
Requires-Dist: cvxpy >=1.1.17
Requires-Dist: anndata
Requires-Dist: scipy
Requires-Dist: numpy
Requires-Dist: pandas
